numpypremium/__init__.py
numpypremium-1.0.0.dist-info/METADATA
numpypremium-1.0.0.dist-info/WHEEL
numpypremium-1.0.0.dist-info/top_level.txt
numpypremium-1.0.0.dist-info/RECORD
