Metadata-Version: 2.1
Name: numpypremium
Version: 1.0.0
Summary: Fundamental package for array computing in Python
Author: charlesr.harri
